karrio/server/graph/schemas/__init__.py
karrio/server/graph/schemas/orders/__init__.py
karrio/server/graph/schemas/orders/inputs.py
karrio/server/graph/schemas/orders/mutations.py
karrio/server/graph/schemas/orders/types.py
karrio/server/orders/__init__.py
karrio/server/orders/admin.py
karrio/server/orders/apps.py
karrio/server/orders/filters.py
karrio/server/orders/models.py
karrio/server/orders/router.py
karrio/server/orders/signals.py
karrio/server/orders/urls.py
karrio/server/orders/views.py
karrio/server/orders/migrations/0001_initial.py
karrio/server/orders/migrations/0002_auto_20211231_2353.py
karrio/server/orders/migrations/0003_alter_order_shipping_address.py
karrio/server/orders/migrations/0004_alter_order_status.py
karrio/server/orders/migrations/0005_auto_20220303_1153.py
karrio/server/orders/migrations/0006_alter_order_shipping_to.py
karrio/server/orders/migrations/0007_alter_order_line_items.py
karrio/server/orders/migrations/0008_alter_order_status.py
karrio/server/orders/migrations/0009_auto_20220321_1535.py
karrio/server/orders/migrations/0010_auto_20220324_2031.py
karrio/server/orders/migrations/0011_order_billing_address.py
karrio/server/orders/migrations/0012_order_order_id_idx.py
karrio/server/orders/migrations/0014_order_meta.py
karrio/server/orders/migrations/0015_remove_order_order_id_idx_alter_order_order_id_and_more.py
karrio/server/orders/migrations/0016_order_shipments.py
karrio/server/orders/migrations/0017_order_order_created_at_idx.py
karrio/server/orders/migrations/0018_ordercounter.py
karrio/server/orders/migrations/0019_orderkey.py
karrio/server/orders/migrations/0020_alter_orderkey_scope.py
karrio/server/orders/migrations/0021_add_json_fields.py
karrio/server/orders/migrations/0022_make_order_fk_nullable.py
karrio/server/orders/migrations/0023_clean_model_refactoring.py
karrio/server/orders/migrations/0024_add_json_indexes.py
karrio/server/orders/migrations/0025_cleanup.py
karrio/server/orders/migrations/__init__.py
karrio_server_orders-2026.1.4.dist-info/METADATA
karrio_server_orders-2026.1.4.dist-info/WHEEL
karrio_server_orders-2026.1.4.dist-info/top_level.txt
karrio_server_orders-2026.1.4.dist-info/RECORD
